Metadata-Version: 1.0
Name: categorical-encoder
Version: 0.1
Summary: Encodes categorical variables
Home-page: https://github.com/ademilly/categorical_encoder
Author: Aurélien Demilly
Author-email: demilly.aurelien@gmail.com
License: MIT
Platform: UNKNOWN
